django_manage_reset_migrations-0.2.dist-info/RECORD
django_manage_reset_migrations-0.2.dist-info/DESCRIPTION.rst
django_manage_reset_migrations-0.2.dist-info/top_level.txt
django_manage_reset_migrations-0.2.dist-info/metadata.json
django_manage_reset_migrations-0.2.dist-info/WHEEL
django_manage_reset_migrations-0.2.dist-info/METADATA
django_manage_reset_migrations/__init__.py
django_manage_reset_migrations/admin.py
django_manage_reset_migrations/tests.py
django_manage_reset_migrations/models.py
django_manage_reset_migrations/views.py
django_manage_reset_migrations/apps.py
django_manage_reset_migrations/migrations/__init__.py
django_manage_reset_migrations/management/__init__.py
django_manage_reset_migrations/management/commands/__init__.py
django_manage_reset_migrations/management/commands/reset_migrations.py
