Metadata-Version: 2.0
Name: django-manage-reset-migrations
Version: 0.2
Summary: A management utility to reset migrations
Home-page: https://github.com/arun6582/django-manage-reset-migrations/
Author: Arun Kumar
Author-email: arun6582@gmail.com
License: UNKNOWN
Platform: UNKNOWN
Classifier: Environment :: Web Environment
Classifier: Framework :: Django
Classifier: Framework :: Django :: 1.9
Classifier: Intended Audience :: Developers
Classifier: Operating System :: OS Independent
Classifier: Programming Language :: Python
Classifier: Programming Language :: Python :: 2
Classifier: Programming Language :: Python :: 2.7
Classifier: Topic :: Internet :: WWW/HTTP
Classifier: Topic :: Internet :: WWW/HTTP :: Dynamic Content
